{"name":"build-javascript","namedChunkGroups":{"app":{"name":"app","assets":[{"name":"webpack-runtime-248ddfcd85273c0958bf.js","size":3984},{"name":"framework-450cf48599bdc978d502.js","size":149628},{"name":"styles.7e7c14a43713dec0a305.css","size":299536},{"name":"app-04251ee3f52d5840ac92.js","size":3000989}],"filteredAssets":0,"assetsSize":3454137,"filteredAuxiliaryAssets":5,"auxiliaryAssetsSize":7627312}},"assetsByChunkName":{"app":["webpack-runtime-248ddfcd85273c0958bf.js","framework-450cf48599bdc978d502.js","styles.7e7c14a43713dec0a305.css","app-04251ee3f52d5840ac92.js"]},"childAssetsByChunkName":{}}